Workbook

Sheet Dashboard
A1: GESTÃO DE EVENTOS - DASHBOARD
A3: INFORMAÇÕES DO EVENTO
A4: Nome do Evento: | B4: Retiro ARS | 2026
A5: Data do Evento: | B5: 13 a 17 de Fevereiro de 2026
A6: Local: | B6: CATRE-Satulina
A7: Número de Participantes: | B7: 105
A9: RESUMO FINANCEIRO
A10: Total de Receitas | B10: =Receitas!E11 -> 59850
A11: Total de Despesas | B11: ='Resumo Despesas'!B10 -> 62800
A12: RESULTADO (Lucro/Prejuízo) | B12: =B10-B11 -> -2950
A13: % Margem de Lucro | B13: =IF(B10=0,0,B12/B10) -> -0.049289891
A15: RESUMO DE TAREFAS
A16: Total de Tarefas | B16: =COUNTA('Cronograma Pré-Evento'!A4:A13)+COUNTA('Cronograma Dia Evento'!A4:A27)+COUNTA('Cronograma Pós-Evento'!A4:A15) -> 36
A17: Concluídas | B17: =COUNTIF('Cronograma Pré-Evento'!E4:E13,"Concluído")+COUNTIF('Cronograma Dia Evento'!E4:E27,"Concluído")+COUNTIF('Cronograma Pós-Evento'!E4:E15,"Concluído") -> 14
A18: Em Andamento | B18: =COUNTIF('Cronograma Pré-Evento'!E4:E13,"Em andamento")+COUNTIF('Cronograma Dia Evento'!E4:E27,"Em andamento")+COUNTIF('Cronograma Pós-Evento'!E4:E15,"Em andamento") -> 9
A19: Pendentes | B19: =COUNTIF('Cronograma Pré-Evento'!E4:E13,"Pendente")+COUNTIF('Cronograma Dia Evento'!E4:E27,"Pendente")+COUNTIF('Cronograma Pós-Evento'!E4:E15,"Pendente") -> 14
A20: Atrasadas | B20: =COUNTIF('Cronograma Pré-Evento'!E4:E13,"Atrasado")+COUNTIF('Cronograma Dia Evento'!E4:E27,"Atrasado")+COUNTIF('Cronograma Pós-Evento'!E4:E15,"Atrasado") -> 9
A22: Quantas Inscrições
A23: Vlr Líquido por inscrito | B23: =600-440-30 -> 130
A24: Precisamos de: | B24: =(B12/B23*-1) -> 22.692308

Sheet Receitas
A1: RECEITAS DO EVENTO
A3: Categoria | B3: Descrição | C3: Valor Unitário | D3: Quantidade | E3: TOTAL
A4: Inscrições | B4: Venda de ingressos participantes | C4: 600 | D4: 105 | E4: =C4*D4 -> 63000
A5: Doações | B5: Doações recebidas | C5: 0 | D5: 0 | E5: =C5*D5 -> 0
A6: Patrocínios | B6: Patrocinadores (Gold, Silver, Bronze) | C6: 0 | D6: 0 | E6: =C6*D6 -> 0
A7: Estandes/Stands | B7: Venda de espaços comerciais | C7: 0 | D7: 0 | E7: =C7*D7 -> 0
A8: Taxa | B8: Venda de produtos do evento | C8: 0 | D8: 0.05 | E8: =(E4*D8)*-1 -> -3150
A9: Outras Receitas | B9: Receitas diversas | C9: 0 | D9: 0 | E9: =C9*D9 -> 0
A11: TOTAL DE RECEITAS | E11: =SUM(E4:E9) -> 59850

Sheet Despesas-Alimentação
A1: DESPESAS - ALIMENTAÇÃO
A3: Item | B3: Descrição | C3: Custo por Pessoa | D3: Qtd Pessoas | E3: Qtd Refeições/Dias | F3: TOTAL
A4: Café da Manhã | B4: Coffee break matinal | C4: 30 | D4: 105 | E4: 4 | F4: =C4*D4*E4 -> 12600
A5: Almoço | B5: Buffet/marmita | C5: 40 | D5: 105 | E5: 4 | F5: =C5*D5*E5 -> 16800
A6: Jantar | B6: Jantar | C6: 40 | D6: 105 | E6: 4 | F6: =C6*D6*E6 -> 16800
A7: Coffee Break | B7: Intervalo (manhã/tarde) | C7: 0 | D7: 0 | E7: 0 | F7: =C7*D7*E7 -> 0
A8: Coquetel | B8: Encerramento/networking | C8: 0 | D8: 0 | E8: 0 | F8: =C8*D8*E8 -> 0
A9: Água/Bebidas | B9: Hidratação geral | C9: 2 | D9: 105 | E9: 1 | F9: =C9*D9*E9 -> 210
A10: Outros | B10: Alimentação extra | C10: 0 | D10: 0 | E10: 0 | F10: =C10*D10*E10 -> 0
A12: SUBTOTAL ALIMENTAÇÃO | F12: =SUM(F4:F10) -> 46410

Sheet Despesas-Estrutura
A1: DESPESAS - ESTRUTURA
A3: Item | B3: Descrição | C3: Valor Unitário | D3: Quantidade | E3: Dias | F3: TOTAL
A4: Locação de Espaço | B4: Auditório/salão | C4: 0 | D4: 1 | E4: 0 | F4: =C4*D4*E4 -> 0
A5: Telão/Projetor | B5: Equipamento audiovisual | C5: 0 | D5: 1 | E5: 0 | F5: =C5*D5*E5 -> 0
A6: Som e Microfones | B6: Sistema de áudio | C6: 0 | D6: 1 | E6: 0 | F6: =C6*D6*E6 -> 0
A7: Iluminação | B7: Iluminação cênica | C7: 0 | D7: 1 | E7: 0 | F7: =C7*D7*E7 -> 0
A8: Infláveis | B8: Crianças e Adultos | C8: 2500 | D8: 1 | E8: 1 | F8: =C8*D8*E8 -> 2500
A9: Cadeiras/Mesas | B9: Mobiliário | C9: 0 | D9: 0 | E9: 0 | F9: =C9*D9*E9 -> 0
A10: Decoração | B10: Flores, painéis, cenografia | C10: 0 | D10: 1 | E10: 0 | F10: =C10*D10*E10 -> 0
A11: Gerador | B11: Energia backup | C11: 0 | D11: 1 | E11: 0 | F11: =C11*D11*E11 -> 0
A12: Banheiros Químicos | B12: Se necessário | C12: 0 | D12: 0 | E12: 0 | F12: =C12*D12*E12 -> 0
A13: Tendas/Coberturas | B13: Área externa | C13: 0 | D13: 0 | E13: 0 | F13: =C13*D13*E13 -> 0
A14: Outros | B14: Estrutura extra | C14: 0 | D14: 0 | E14: 0 | F14: =C14*D14*E14 -> 0
A16: SUBTOTAL ESTRUTURA | F16: =SUM(F4:F14) -> 2500

Sheet Despesas-Palestrantes
A1: DESPESAS - PALESTRANTES
A3: Nome do Palestrante | B3: Tema | C3: Cachê | D3: Passagens | E3: Hospedagem | F3: TOTAL
A4: Palestrante 1 | B4: Fernando Iglesias | C4: 12090 | D4: 0 | E4: 0 | F4: =C4+D4+E4 -> 12090
A5: Palestrante 2 | C5: 0 | D5: 0 | E5: 0 | F5: =C5+D5+E5 -> 0
A6: Palestrante 3 | C6: 0 | D6: 0 | E6: 0 | F6: =C6+D6+E6 -> 0
A7: Palestrante 4 | C7: 0 | D7: 0 | E7: 0 | F7: =C7+D7+E7 -> 0
A8: Outros | C8: 0 | D8: 0 | E8: 0 | F8: =C8+D8+E8 -> 0
A10: SUBTOTAL PALESTRANTES | F10: =SUM(F4:F8) -> 12090

Sheet Despesas-Cantores
A1: DESPESAS - CANTORES/ARTISTAS
A3: Nome do Artista | B3: Tipo (Cantor) | C3: Cachê | D3: Passagens | E3: Rider Técnico | F3: TOTAL
A4: Cantor 1 | B4: Quarteto | C4: 1000 | D4: 0 | E4: 0 | F4: =C4+D4+E4 -> 1000
A5: Cantor 2 | C5: 0 | D5: 0 | E5: 0 | F5: =C5+D5+E5 -> 0
A6: Cantor 3 | C6: 0 | D6: 0 | E6: 0 | F6: =C6+D6+E6 -> 0
A7: Banda | C7: 0 | D7: 0 | E7: 0 | F7: =C7+D7+E7 -> 0
A8: Outros | C8: 0 | D8: 0 | E8: 0 | F8: =C8+D8+E8 -> 0
A10: SUBTOTAL ARTISTAS | F10: =SUM(F4:F8) -> 1000

Sheet Despesas-Operacionais
A1: DESPESAS - OPERACIONAIS
A3: Item | B3: Descrição | C3: Valor Unitário | D3: Quantidade | E3: TOTAL
A4: Dinâmica | B4: Ecobags, canetas, etc | C4: 1 | D4: 500 | E4: =C4*D4 -> 500
A5: Cesta Fernando Iglesias | B5: Cesta Quarto | C5: 1 | D5: 300 | E5: =C5*D5 -> 300
A6: Crachás | B6: Identificação | C6: 0 | D6: 0 | E6: =C6*D6 -> 0
A7: Impressos | B7: Programação, folders | C7: 0 | D7: 0 | E7: =C7*D7 -> 0
A8: Marketing | B8: Anúncios, redes sociais | C8: 0 | D8: 0 | E8: =C8*D8 -> 0
A9: Equipe/Staff | B9: Recepção, apoio | C9: 0 | D9: 0 | E9: =C9*D9 -> 0
A10: Segurança | B10: Seguranças | C10: 0 | D10: 0 | E10: =C10*D10 -> 0
A11: Limpeza | B11: Equipe de limpeza | C11: 0 | D11: 0 | E11: =C11*D11 -> 0
A12: Seguros | B12: Seguro do evento | C12: 0 | D12: 0 | E12: =C12*D12 -> 0
A13: Ambulância/Primeiros Socorros | B13: Equipe médica | C13: 0 | D13: 0 | E13: =C13*D13 -> 0
A14: Transporte | B14: Transfer/fretado | C14: 0 | D14: 0 | E14: =C14*D14 -> 0
A15: Certificados | B15: Impressão certificados | C15: 0 | D15: 0 | E15: =C15*D15 -> 0
... A18: Outros | B18: Despesas diversas | C18: 0 | D18: 0 | E18: =C18*D18 -> 0
A20: SUBTOTAL OPERACIONAIS | E20: =SUM(E4:E18) -> 800

Sheet Resumo Despesas
A1: RESUMO GERAL DE DESPESAS
A3: Categoria | B3: Total
A4: Alimentação | B4: ='Despesas-Alimentação'!F12 -> 46410
A5: Estrutura | B5: ='Despesas-Estrutura'!F16 -> 2500
A6: Palestrantes | B6: ='Despesas-Palestrantes'!F10 -> 12090
A7: Cantores | B7: ='Despesas-Cantores'!F10 -> 1000
A8: Operacionais | B8: ='Despesas-Operacionais'!E20 -> 800
A10: TOTAL GERAL | B10: =SUM(B4:B8) -> 62800

Sheet Cronograma Pré-Evento
A1: CRONOGRAMA PRÉ-EVENTO
A3: Tarefa | B3: Responsável | C3: Data Início | D3: Data Fim | E3: Status | F3: Observações
A4: Definir data e local | B4: Maicon Galantini | E4: Concluído | F4: Contrato fechado
A5: Contratar palestrantes | B5: Maicon Galantini | E5: Concluído | F5: Aguardando confirmação 2 palestrantes
A6: Abrir inscrições | B6: Maicon Galantini | E6: Concluído | F6: Site em desenvolvimento
A7: Contratar estrutura | B7: Maicon Galantini | E7: Concluído | F7: Solicitar orçamentos
A8: Fechar cardápio | B8: Jacqueline França | E8: Pendente | F8: Definir menu
A9: Material gráfico | B9: Maicon Galantini | E9: Pendente | F9: Crachás e folders
A10: Divulgação | B10: Maicon Galantini | E10: Concluído | F10: Campanha redes sociais
A11: Comprar brindes | B11: x | E11: Pendente | F11: Cotação pendente
A12: Confirmação inscritos | B12: x | E12: Pendente | F12: Enviar e-mails
A13: Reunião geral equipe | B13: x | E13: Pendente | F13: Alinhamento final

Sheet Cronograma Dia Evento
A1: CRONOGRAMA DIA DO EVENTO
A3: Tarefa | B3: Responsável | C3: Data Início | D3: Data Fim | E3: Status | F3: Observações
A4: 06:00 - Chegada equipe montagem | B4: xx | E4: Atrasado | F4: Equipe técnica
A5: 07:00 - Montagem estrutura | B5: Equipe técnica | E5: Em andamento | F5: Som, telão, iluminação
A6: 08:00 - Teste de som e imagem | B6: Pedro Costa | E6: Concluído | F6: Verificar equipamentos
A7: 08:30 - Montagem coffee break | B7: Ana Lima | E7: Pendente | F7: Hall entrada
A8: 09:00 - Abertura credenciamento | B8: Maria Santos | E8: Atrasado | F8: Recepção participantes
A9: 09:30 - Início evento - Abertura | B9: João Silva | E9: Em andamento | F9: Palavras iniciais
A10: 10:00 - Palestra 1 | B10: Palestrante A | E10: Concluído | F10: Tema 1
A11: 10:45 - Coffee break | B11: Todos | E11: Pendente | F11: Intervalo 15min
A12: 11:00 - Palestra 2 | B12: Palestrante B | E12: Atrasado | F12: Tema 2
A13: 12:00 - Almoço | B13: Todos | E13: Em andamento | F13: Restaurante buffet
A14: 14:00 - Palestra 3 | B14: Palestrante C | E14: Concluído | F14: Tema 3
A15: 15:30 - Coffee break | B15: Todos | E15: Pendente | F15: Intervalo tarde
... A20: 20:00 - Desmontagem | B20: Equipe técnica | E20: Atrasado | F20: Recolher equipamentos
E21: Em andamento
E22: Concluído
E23: Pendente
E24: Atrasado
E25: Em andamento
E26: Concluído
E27: Pendente

Sheet Cronograma Pós-Evento
A1: CRONOGRAMA PÓS-EVENTO
A3: Tarefa | B3: Responsável | C3: Data Início | D3: Data Fim | E3: Status | F3: Observações
A4: Pesquisa de satisfação | B4: x | E4: Atrasado | F4: Enviar formulário online
A5: Emissão de certificados | B5: x | E5: Em andamento | F5: Gerar e enviar por e-mail
A6: Relatório financeiro | B6: x | E6: Concluído | F6: Fechar contas do evento
A7: Relatório de resultados | B7: x | E7: Pendente | F7: Consolidar dados
A8: Agradecimentos participantes | B8: x | E8: Atrasado | F8: E-mail de agradecimento
A9: Agradecimentos patrocinadores | B9: x | E9: Em andamento | F9: E-mail + relatório
A10: Fotos e vídeos | B10: x | E10: Concluído | F10: Editar e publicar
A11: Post-mortem | B11: x | E11: Pendente | F11: Reunião lições aprendidas
A12: Arquivo documentos | B12: x | E12: Atrasado | F12: Organizar contratos e notas
E13: Em andamento
E14: Concluído
E15: Pendente

Sheet Rastreamento Responsável
A1: RASTREAMENTO POR RESPONSÁVEL
A3: Responsável | B3: Tarefa | C3: Cronograma | D3: Data Início | E3: Data Fim | F3: Status
A4: x | B4: Definir data e local | C4: Pré-Evento | F4: Atrasado
A5: x | B5: Início evento - Abertura | C5: Dia Evento | F5: Em andamento
A6: x | B6: Relatório financeiro | C6: Pós-Evento | F6: Concluído
A7: x | B7: Contratar palestrantes | C7: Pré-Evento | F7: Pendente
A8: x | B8: Abertura credenciamento | C8: Dia Evento | F8: Atrasado
A9: x | B9: Pesquisa de satisfação | C9: Pós-Evento | F9: Em andamento
A10: x | B10: Abrir inscrições | C10: Pré-Evento | F10: Concluído
A11: x | B11: Contratar estrutura | C11: Pré-Evento | F11: Pendente
A12: x | B12: Divulgação | C12: Pré-Evento | F12: Atrasado
A13: x | B13: Chegada equipe montagem | C13: Dia Evento | F13: Em andamento
F14: Concluído
F15: Pendente

Sheet Planilha3
A1: NOTAS
A3: Responsável | B3: Item | C3: Observação | D3: Status
B4: Refeição | C4: Jack pediu para aumentar 10,00 em cada refeição e 20,00 para refeição vegana | D4: Pendente
B5: Equipe de Apoio | C5: Brayan, Pr. Bruno e Família e Pr. Ricardo e Família | D5: Pendente
D6: Pendente

Sheet NOTES
A4: Pendente
A5: Concluído
A6: Em andamento
A7: Atrasado
